pydappdb/__init__.py
pydappdb-0.2.dist-info/License.txt
pydappdb-0.2.dist-info/METADATA
pydappdb-0.2.dist-info/WHEEL
pydappdb-0.2.dist-info/top_level.txt
pydappdb-0.2.dist-info/RECORD
