Metadata-Version: 2.1
Name: pydappdb
Version: 0.2
Summary: lets you store data on a decentralized network.
Author: Abhirath Dubey
Author-email: abhirathdubey2804@gmail.com
License: UNKNOWN
Platform: UNKNOWN
License-File: License.txt
Requires-Dist: requests
